dmstockapi/__init__.py
dmstockapi/api_client.py
dmstockapi/constant.py
dmstockapi/exceptions.py
dmstockapi/future_client.py
dmstockapi/future_model.py
dmstockapi/price_client.py
dmstockapi/price_model.py
dmstockapi/stock_client.py
dmstockapi/stock_model.py
dmstockapi2-0.4.2.dist-info/METADATA
dmstockapi2-0.4.2.dist-info/WHEEL
dmstockapi2-0.4.2.dist-info/top_level.txt
dmstockapi2-0.4.2.dist-info/RECORD
